sunsoft/__init__.py
sunsoft/tracking.py
sunsoft_utils-0.1.0.dist-info/METADATA
sunsoft_utils-0.1.0.dist-info/WHEEL
sunsoft_utils-0.1.0.dist-info/top_level.txt
sunsoft_utils-0.1.0.dist-info/RECORD
