Metadata-Version: 2.2
Name: sunsoft-utils
Version: 0.1.0
Summary: Shared utilities for Sunsoft packages
Home-page: https://github.com/greatbody/macpy-scripts
Author: greatbody
Author-email: sunruicode@gmail.com
Classifier: Programming Language :: Python :: 3
Classifier: Programming Language :: Python :: 3.8
Classifier: Programming Language :: Python :: 3.9
Classifier: Programming Language :: Python :: 3.10
Classifier: Programming Language :: Python :: 3.11
Classifier: License :: OSI Approved :: MIT License
Classifier: Operating System :: OS Independent
Classifier: Development Status :: 4 - Beta
Classifier: Intended Audience :: Developers
Requires-Python: >=3.8
Requires-Dist: requests>=2.32.3
Requires-Dist: termcolor>=2.3.0
Dynamic: author
Dynamic: author-email
Dynamic: classifier
Dynamic: description
Dynamic: description-content-type
Dynamic: home-page
Dynamic: requires-dist
Dynamic: requires-python
Dynamic: summary
